fastapi_create_app/__init__.py
fastapi_create_app/main.py
fastapi_create_app-1.1.0.dist-info/entry_points.txt
fastapi_create_app-1.1.0.dist-info/WHEEL
fastapi_create_app-1.1.0.dist-info/METADATA
fastapi_create_app-1.1.0.dist-info/RECORD
