Metadata-Version: 2.1
Name: fastapi-create-app
Version: 1.1.0
Summary: A CLI to generate bare-bone FastAPI project
Author: kenmoh
Author-email: kenneth.aremoh@gmail.com
Requires-Python: >=3.10,<4.0
Classifier: Programming Language :: Python :: 3
Classifier: Programming Language :: Python :: 3.10
Classifier: Programming Language :: Python :: 3.11
Requires-Dist: typer[all] (>=0.7.0,<0.8.0)
